easy_py_server/__init__.py
easy_py_server/datastruct.py
easy_py_server/exception.py
easy_py_server/server.py
easy_py_server-1.2.2.dist-info/LICENSE
easy_py_server-1.2.2.dist-info/METADATA
easy_py_server-1.2.2.dist-info/WHEEL
easy_py_server-1.2.2.dist-info/top_level.txt
easy_py_server-1.2.2.dist-info/RECORD
